token_exchange/__init__.py
token_exchange/admin.py
token_exchange/apps.py
token_exchange/auth.py
token_exchange/models.py
token_exchange/plugin.py
token_exchange/signals.py
token_exchange/migrations/0001_initial.py
token_exchange/migrations/0002_tokenexchangeconfiguration_label.py
token_exchange/migrations/__init__.py
token_exchange/tests/__init__.py
token_exchange/tests/factories.py
token_exchange/tests/test_custom_auth.py
token_exchange/tests/test_models.py
token_exchange/tests/test_plugin.py
token_exchange/tests/test_signals.py
open_forms_ext_token_exchange-0.4.0.dist-info/LICENSE
open_forms_ext_token_exchange-0.4.0.dist-info/METADATA
open_forms_ext_token_exchange-0.4.0.dist-info/WHEEL
open_forms_ext_token_exchange-0.4.0.dist-info/top_level.txt
open_forms_ext_token_exchange-0.4.0.dist-info/RECORD
